dspftw/__init__.py
dspftw/complex_sinusoid.py
dspftw/data_types.py
dspftw/decimal_convert_to_base.py
dspftw/endianness.py
dspftw/exceptions.py
dspftw/filename_load.py
dspftw/find_peaks.py
dspftw/generate_qam.py
dspftw/generate_random_qpsk.py
dspftw/load_bits.py
dspftw/load_data.py
dspftw/load_signal.py
dspftw/raised_cosine_filter_generator.py
dspftw/root_raised_cosine.py
dspftw/root_raised_cosine_filter_generator.py
dspftw/rounding.py
dspftw/save_bits.py
dspftw/save_data.py
dspftw/save_signal.py
dspftw/signal_correlation.py
dspftw/signal_types.py
dspftw/test_qpsk_modulation.py
dspftw/truncation.py
dspftw/vector_power.py
dspftw/writemode.py
dspftw-2024.272.181.dist-info/LICENSE
dspftw-2024.272.181.dist-info/METADATA
dspftw-2024.272.181.dist-info/WHEEL
dspftw-2024.272.181.dist-info/RECORD
