Metadata-Version: 2.1
Name: dspftw
Version: 2024.272.181
Summary: Starting points and helper functions for learning digital signal processing.
Home-page: http://github.com/dspftw/dspftw
License: MIT
Author: Bill Allen
Author-email: billallen256@gmail.com
Requires-Python: >=3.7,<4.0
Classifier: License :: OSI Approved :: MIT License
Classifier: Programming Language :: Python :: 3
Classifier: Programming Language :: Python :: 3.7
Classifier: Programming Language :: Python :: 3.8
Classifier: Programming Language :: Python :: 3.9
Classifier: Programming Language :: Python :: 3.10
Classifier: Programming Language :: Python :: 3.11
Classifier: Programming Language :: Python :: 3.12
Requires-Dist: numpy (>=1.20.0,<2.0.0)
Requires-Dist: scipy (>=1.6.3,<2.0.0)
